tests/__init__.py
tests/test_cli.py
tests/test_config_helper.py
tests/test_troubleshooter.py
tests/test_utils.py
tshoot/__init__.py
tshoot/cli.py
tshoot/config.py
tshoot/config_helper.py
tshoot/prompts.py
tshoot/troubleshooter.py
tshoot/utils.py
tshoot-0.1.0.dist-info/METADATA
tshoot-0.1.0.dist-info/WHEEL
tshoot-0.1.0.dist-info/entry_points.txt
tshoot-0.1.0.dist-info/licenses/LICENSE
tshoot-0.1.0.dist-info/RECORD
