Metadata-Version: 2.1
Name: tshoot
Version: 0.1.0
Summary: A simple CLI commands to try troubleshooting errors with LLMs
Project-URL: Documentation, https://di3go-sona.github.io/tshoot/
Project-URL: Source, https://github.com/di3go-sona/tshoot
Author-email: tshoot <diego.sonaglia@gmail.com>
License-File: LICENSE
Classifier: Programming Language :: Python :: 3 :: Only
Requires-Python: >=3.9
Requires-Dist: dynaconf
Requires-Dist: inquirerpy
Requires-Dist: openai
